sentsplit/__init__.py
sentsplit/cli.py
sentsplit/config.py
sentsplit/meta_data.py
sentsplit/regexes.py
sentsplit/segment.py
sentsplit/train.py
sentsplit/utils.py
sentsplit/crf_models/de-default-25032021.model
sentsplit/crf_models/en-default-25032021.model
sentsplit/crf_models/fr-default-25032021.model
sentsplit/crf_models/it-default-25032021.model
sentsplit/crf_models/ja-default-05042021.model
sentsplit/crf_models/ja-default-25032021.model
sentsplit/crf_models/ko-default-05042021.model
sentsplit/crf_models/ko-default-25032021.model
sentsplit/crf_models/ko-default-27032021.model
sentsplit/crf_models/lt-default-25032021.model
sentsplit/crf_models/pl-default-25032021.model
sentsplit/crf_models/pt-default-25032021.model
sentsplit/crf_models/ru-default-25032021.model
sentsplit/crf_models/tr-default-25032021.model
sentsplit/crf_models/zh-default-05042021.model
sentsplit/crf_models/zh-default-25032021.model
sentsplit-1.0.3.dist-info/LICENSE
sentsplit-1.0.3.dist-info/METADATA
sentsplit-1.0.3.dist-info/WHEEL
sentsplit-1.0.3.dist-info/entry_points.txt
sentsplit-1.0.3.dist-info/top_level.txt
sentsplit-1.0.3.dist-info/RECORD
